{
  "items": [
    {
      "date": "2026-06-09",
      "ranks": {}
    },
    {
      "date": "2026-07-01",
      "ranks": {
        "BK1424": 1,
        "BK1358": 6,
        "BK1489": 2,
        "BK1511": 3,
        "BK1503": 4,
        "BK1443": 5,
        "BK0474": 7,
        "BK1412": 8,
        "BK1491": 9,
        "BK1259": 10,
        "BK0882": 11,
        "BK1465": 12
      }
    },
    {
      "date": "2026-07-02",
      "ranks": {
        "BK1617": 3,
        "BK0732": 5,
        "BK1424": 6,
        "BK1351": 1,
        "BK1509": 2,
        "BK1348": 4,
        "BK1625": 7,
        "BK1499": 8,
        "BK1295": 9,
        "BK1395": 10,
        "BK1413": 11,
        "BK1416": 12
      }
    },
    {
      "date": "2026-07-03",
      "ranks": {
        "BK1408": 1,
        "BK1617": 2,
        "BK1145": 3,
        "BK0732": 4,
        "BK1385": 5,
        "BK1232": 6,
        "BK1100": 7,
        "BK1295": 8,
        "BK1307": 9,
        "BK1030": 10,
        "BK1099": 11,
        "BK1383": 12
      }
    },
    {
      "date": "2026-07-05",
      "ranks": {
        "BK1408": 1,
        "BK1617": 2,
        "BK1145": 3,
        "BK0732": 4,
        "BK1385": 5,
        "BK1232": 6,
        "BK1100": 7,
        "BK1295": 8,
        "BK1307": 9,
        "BK1030": 10,
        "BK1099": 11,
        "BK1383": 12
      }
    },
    {
      "date": "2026-07-06",
      "ranks": {
        "BK1512": 3,
        "BK1493": 4,
        "BK1250": 5,
        "BK1569": 6,
        "BK1412": 1,
        "BK1305": 2,
        "BK1259": 7,
        "BK1620": 8,
        "BK0437": 9,
        "BK0882": 10,
        "BK1494": 11,
        "BK0946": 12
      }
    },
    {
      "date": "2026-07-07",
      "ranks": {
        "BK1328": 2,
        "BK1326": 6,
        "BK1325": 8,
        "BK1348": 1,
        "BK1645": 7,
        "BK1121": 3,
        "BK1611": 10,
        "BK1506": 4,
        "BK1257": 5,
        "BK1305": 9,
        "BK1327": 11,
        "BK1329": 12
      }
    },
    {
      "date": "2026-07-08",
      "ranks": {
        "BK0885": 1,
        "BK1008": 3,
        "BK0897": 5,
        "BK1448": 8,
        "BK1051": 9,
        "BK1573": 2,
        "BK1348": 4,
        "BK1275": 6,
        "BK1132": 10,
        "BK1297": 7,
        "BK1562": 11,
        "BK1189": 12
      }
    },
    {
      "date": "2026-07-09",
      "ranks": {
        "BK1325": 1,
        "BK1328": 2,
        "BK1329": 3,
        "BK1152": 5,
        "BK1326": 6,
        "BK1101": 7,
        "BK1713": 8,
        "BK1137": 9,
        "BK1036": 10,
        "BK1443": 4,
        "BK0935": 11,
        "BK1121": 12
      }
    },
    {
      "date": "2026-07-10",
      "ranks": {
        "BK1385": 1,
        "BK1232": 2,
        "BK1600": 3,
        "BK1383": 5,
        "BK1230": 6,
        "BK0727": 9,
        "BK0899": 10,
        "BK1314": 7,
        "BK1602": 8,
        "BK1300": 4,
        "BK1321": 11,
        "BK1296": 12
      }
    },
    {
      "date": "2026-07-13",
      "ranks": {
        "BK1608": 2,
        "BK1040": 3,
        "BK1656": 4,
        "BK0676": 8,
        "BK1611": 7,
        "BK1609": 10,
        "BK1645": 1,
        "BK1574": 5,
        "BK1276": 6,
        "BK1612": 9,
        "BK1283": 11,
        "BK0475": 12
      }
    },
    {
      "date": "2026-07-14",
      "ranks": {
        "BK1462": 4,
        "BK1340": 6,
        "BK1630": 7,
        "BK0459": 8,
        "BK1574": 2,
        "BK1276": 3,
        "BK1573": 9,
        "BK1275": 5,
        "BK1572": 1,
        "BK1295": 10,
        "BK1416": 11,
        "BK1017": 12
      }
    },
    {
      "date": "2026-07-15",
      "ranks": {
        "BK1600": 4,
        "BK0899": 8,
        "BK0727": 9,
        "BK1300": 2,
        "BK0816": 6,
        "BK1051": 10,
        "BK1500": 3,
        "BK1253": 5,
        "BK1645": 1,
        "BK1507": 7,
        "BK1063": 11,
        "BK1146": 12
      }
    },
    {
      "date": "2026-07-16",
      "ranks": {
        "BK1645": 2,
        "BK1222": 3,
        "BK1300": 1,
        "BK1299": 4,
        "BK1599": 8,
        "BK1500": 5,
        "BK1601": 10,
        "BK1253": 11,
        "BK1298": 12,
        "BK1555": 6,
        "BK1270": 7,
        "BK1296": 9
      },
      "amounts": {
        "BK1645": 1946330152.0,
        "BK1222": 8709321143.0,
        "BK1300": 2137993176.0,
        "BK1299": 6571327967.0,
        "BK1599": 1168255917.0,
        "BK1500": 1717495929.0,
        "BK1601": 5745386918.0,
        "BK1253": 1729719412.0,
        "BK1298": 1500145132.0,
        "BK1555": 1839080136.0,
        "BK1270": 1839080136.0,
        "BK1296": 435889746.0
      }
    },
    {
      "date": "2026-07-17",
      "ranks": {
        "BK1645": 1,
        "BK1051": 3,
        "BK1380": 4,
        "BK0816": 6,
        "BK1377": 8,
        "BK0428": 9,
        "BK1373": 5,
        "BK1611": 7,
        "BK1412": 11,
        "BK1374": 12,
        "BK1565": 2,
        "BK1432": 10
      },
      "amounts": {
        "BK1645": 10534988337.0,
        "BK1051": 14434273947.0,
        "BK1380": 12592548679.0,
        "BK0816": 14421983835.0,
        "BK1377": 25006876237.0,
        "BK0428": 61219035430.0,
        "BK1373": 4843197731.0,
        "BK1611": 16249023990.0,
        "BK1412": 451845140.0,
        "BK1374": 7676347837.0,
        "BK1565": 311691101.0,
        "BK1432": 2497588047.0
      }
    },
    {
      "date": "2026-07-20",
      "ranks": {
        "BK1377": 5,
        "BK1373": 6,
        "BK1250": 10,
        "BK1275": 2,
        "BK1574": 3,
        "BK1276": 4,
        "BK1573": 9,
        "BK1572": 1,
        "BK1494": 8,
        "BK1493": 11,
        "BK1380": 12,
        "BK1347": 7
      },
      "amounts": {
        "BK1377": 33743339098.0,
        "BK1373": 6880732353.0,
        "BK1250": 16028487471.0,
        "BK1275": 7948649244.0,
        "BK1574": 4917913660.0,
        "BK1276": 4917913660.0,
        "BK1573": 3367135764.0,
        "BK1572": 4581513480.0,
        "BK1494": 3564418578.0,
        "BK1493": 12464068893.0,
        "BK1380": 13905446554.0,
        "BK1347": 261965509.0
      }
    },
    {
      "date": "2026-07-21",
      "ranks": {
        "BK1326": 1,
        "BK1152": 2,
        "BK1325": 3,
        "BK1329": 4,
        "BK0536": 5,
        "BK1328": 6,
        "BK1036": 7,
        "BK1327": 8,
        "BK0890": 9,
        "BK1713": 10,
        "BK0935": 11,
        "BK1059": 12
      },
      "amounts": {
        "BK1326": 84653779307.0,
        "BK1152": 103163504585.0,
        "BK1325": 57701665076.0,
        "BK1329": 43928361264.0,
        "BK0536": 191154731178.0,
        "BK1328": 58919455453.0,
        "BK1036": 520600196787.0,
        "BK1327": 38345045508.0,
        "BK0890": 63644354870.0,
        "BK1713": 857986066562.0,
        "BK0935": 214693929999.0,
        "BK1059": 835161197727.0
      }
    },
    {
      "date": "2026-07-22",
      "ranks": {
        "BK0732": 4,
        "BK1617": 5,
        "BK1645": 1,
        "BK1051": 2,
        "BK0816": 7,
        "BK1434": 6,
        "BK1412": 9,
        "BK1318": 11,
        "BK1573": 12,
        "BK1616": 3,
        "BK1500": 8,
        "BK1253": 10
      },
      "amounts": {
        "BK0732": 26739980257.0,
        "BK1617": 20850419480.0,
        "BK1645": 3563678920.0,
        "BK1051": 6662363021.0,
        "BK0816": 5214461947.0,
        "BK1434": 6086697314.0,
        "BK1412": 777841653.0,
        "BK1318": 3877240213.0,
        "BK1573": 3101867811.0,
        "BK1616": 5889560777.0,
        "BK1500": 1947466256.0,
        "BK1253": 1962198537.0
      }
    },
    {
      "date": "2026-07-23",
      "ranks": {
        "BK1311": 1,
        "BK1621": 2,
        "BK1312": 3,
        "BK0457": 7,
        "BK1015": 8,
        "BK1645": 9,
        "BK1382": 4,
        "BK1229": 5,
        "BK0818": 10,
        "BK1616": 6,
        "BK1469": 11,
        "BK1320": 12
      },
      "amounts": {
        "BK1311": 21823099593.0,
        "BK1621": 16401351481.0,
        "BK1312": 16044160009.0,
        "BK0457": 56331066665.0,
        "BK1015": 20991565472.0,
        "BK1645": 6663206743.0,
        "BK1382": 4524770397.0,
        "BK1229": 4524770397.0,
        "BK0818": 2506949305.0,
        "BK1616": 6878607147.0,
        "BK1469": 233155865.0,
        "BK1320": 16379859089.0
      }
    },
    {
      "date": "2026-07-24",
      "ranks": {
        "BK1051": 1,
        "BK1676": 2,
        "BK1674": 3,
        "BK0816": 5,
        "BK1050": 7,
        "BK1630": 9,
        "BK0815": 10,
        "BK1645": 11,
        "BK1503": 12,
        "BK1573": 4,
        "BK1275": 6,
        "BK1572": 8
      },
      "amounts": {
        "BK1051": 738236938.0,
        "BK1676": 113370003.0,
        "BK1674": 258398452.0,
        "BK0816": 674131373.0,
        "BK1050": 2402482745.0,
        "BK1630": 1635784122.0,
        "BK0815": 2092979010.0,
        "BK1645": 523405369.0,
        "BK1503": 11450403.0,
        "BK1573": 104625803.0,
        "BK1275": 186408323.0,
        "BK1572": 81782520.0
      }
    }
  ]
}