{
  "meta": {
    "schemaVersion": 4,
    "generatedAt": "2026-07-13T09:38:24.338191+08:00",
    "tradingDate": "2026-07-13",
    "mode": "fast-snapshot",
    "sourceHealth": [
      {
        "name": "Eastmoney",
        "ok": true,
        "url": "https://push2delay.eastmoney.com/api/qt/clist/get?pn=1&pz=5000&po=1&np=1&ut=bd1d9ddb04089700cf9c27f6f7426281&fltt=2&invt=2&fid=f3&fs=m%3A0%2Bt%3A6%2Cm%3A0%2Bt%3A80%2Cm%3A1%2Bt%3A2%2Cm%3A1%2Bt%3A23&fields=f12%2Cf13%2Cf14%2Cf2%2Cf3%2Cf4%2Cf5%2Cf6%2Cf7%2Cf8%2Cf10%2Cf15%2Cf16%2Cf17%2Cf18%2Cf20%2Cf21%2Cf62%2Cf66%2Cf100",
        "note": "OK"
      },
      {
        "name": "Eastmoney News",
        "ok": true,
        "url": "https://finance.eastmoney.com/a/cjjsp.html",
        "note": "Optional news source OK"
      },
      {
        "name": "10jqka",
        "ok": true,
        "url": "https://stock.10jqka.com.cn/",
        "note": "Optional news source OK"
      },
      {
        "name": "Yicai",
        "ok": true,
        "url": "https://www.yicai.com/news/",
        "note": "Optional news source OK"
      }
    ],
    "errors": [],
    "runtimeSeconds": 81.74
  },
  "market": {
    "recommendationCount": 1,
    "qualifiedBoardCount": 6,
    "monitor": {
      "emotionScore": 99,
      "riskLevel": "NORMAL",
      "limitUpCount": 20,
      "limitDownCount": 0,
      "bigDownCount": 0,
      "limitTouchCount": 26,
      "brokenBoardCount": 6,
      "brokenBoardRate": 0.231,
      "topBoardPct": 2.26,
      "note": "RISK_OFF blocks new buys; CAUTION keeps only high-edge candidates."
    }
  },
  "boards": [
    {
      "code": "BK0981",
      "name": "工业气体",
      "kind": "Concept board",
      "price": 3249.61,
      "pct": 2.26,
      "amount": 10504160751.0,
      "turnover": 0.85,
      "open": 3229.35,
      "preClose": 3177.93,
      "mainNet": -159134816.0,
      "rank": 8,
      "passed": 5,
      "qualified": true,
      "score": 97.2,
      "criteria": [
        "[SectorGate] Board rank stays in the front row",
        "[SectorGate] Limit-up ladder or 5%+ cohort exists",
        "[SectorGate] Board turnover amount is active",
        "[SectorGate] Leaders have follow-through support",
        "[SectorGate] Board momentum remains top-15 positive"
      ],
      "limitUpCount": 2,
      "bigUpCount": 9
    },
    {
      "code": "BK0949",
      "name": "氦气概念",
      "kind": "Concept board",
      "price": 3646.58,
      "pct": 5.52,
      "amount": 6830208046.0,
      "turnover": 2.06,
      "open": 3593.85,
      "preClose": 3455.91,
      "mainNet": 103456064.0,
      "rank": 2,
      "passed": 4,
      "qualified": true,
      "score": 82.9,
      "criteria": [
        "[SectorGate] Board rank stays in the front row",
        "[SectorGate] Limit-up ladder or 5%+ cohort exists",
        "[SectorGate] Leaders have follow-through support",
        "[SectorGate] Board momentum remains top-15 positive"
      ],
      "limitUpCount": 5,
      "bigUpCount": 10
    },
    {
      "code": "BK0816",
      "name": "昨日连板",
      "kind": "Concept board",
      "price": 19888.08,
      "pct": 4.06,
      "amount": 1502065645.0,
      "turnover": 4.09,
      "open": 19887.82,
      "preClose": 19111.35,
      "mainNet": -45908361.0,
      "rank": 3,
      "passed": 4,
      "qualified": true,
      "score": 82.55,
      "criteria": [
        "[SectorGate] Board rank stays in the front row",
        "[SectorGate] Limit-up ladder or 5%+ cohort exists",
        "[SectorGate] Leaders have follow-through support",
        "[SectorGate] Board momentum remains top-15 positive"
      ],
      "limitUpCount": 3,
      "bigUpCount": 3
    },
    {
      "code": "BK1051",
      "name": "昨日连板_含一字",
      "kind": "Concept board",
      "price": 29031.33,
      "pct": 3.56,
      "amount": 2414431733.0,
      "turnover": 2.91,
      "open": 28906.11,
      "preClose": 28033.81,
      "mainNet": -49615616.0,
      "rank": 4,
      "passed": 4,
      "qualified": true,
      "score": 82.2,
      "criteria": [
        "[SectorGate] Board rank stays in the front row",
        "[SectorGate] Limit-up ladder or 5%+ cohort exists",
        "[SectorGate] Leaders have follow-through support",
        "[SectorGate] Board momentum remains top-15 positive"
      ],
      "limitUpCount": 3,
      "bigUpCount": 4
    },
    {
      "code": "BK1028",
      "name": "燃气Ⅱ",
      "kind": "Industry board",
      "price": 1801.98,
      "pct": 2.03,
      "amount": 1093940065.0,
      "turnover": 0.43,
      "open": 1787.95,
      "preClose": 1766.13,
      "mainNet": 107298131.0,
      "rank": 9,
      "passed": 4,
      "qualified": true,
      "score": 80.45,
      "criteria": [
        "[SectorGate] Board rank stays in the front row",
        "[SectorGate] Limit-up ladder or 5%+ cohort exists",
        "[SectorGate] Leaders have follow-through support",
        "[SectorGate] Board momentum remains top-15 positive"
      ],
      "limitUpCount": 2,
      "bigUpCount": 3
    },
    {
      "code": "BK1381",
      "name": "燃气Ⅲ",
      "kind": "Industry board",
      "price": 1801.92,
      "pct": 2.03,
      "amount": 1091244410.0,
      "turnover": 0.43,
      "open": 1787.95,
      "preClose": 1766.13,
      "mainNet": 107298131.0,
      "rank": 10,
      "passed": 4,
      "qualified": true,
      "score": 80.1,
      "criteria": [
        "[SectorGate] Board rank stays in the front row",
        "[SectorGate] Limit-up ladder or 5%+ cohort exists",
        "[SectorGate] Leaders have follow-through support",
        "[SectorGate] Board momentum remains top-15 positive"
      ],
      "limitUpCount": 2,
      "bigUpCount": 3
    },
    {
      "code": "BK1645",
      "name": "昨日打二板以上表现",
      "kind": "Concept board",
      "price": 6989.54,
      "pct": 10.02,
      "amount": 456432664.0,
      "turnover": 9.12,
      "open": 6063.3,
      "preClose": 6353.04,
      "mainNet": 2606727.0,
      "rank": 1,
      "passed": 2,
      "qualified": false,
      "score": 50.45,
      "criteria": [
        "[SectorGate] Board rank stays in the front row",
        "[SectorGate] Board momentum remains top-15 positive"
      ],
      "limitUpCount": 1,
      "bigUpCount": 1
    },
    {
      "code": "BK1625",
      "name": "钨",
      "kind": "Industry board",
      "price": 9670.52,
      "pct": 2.74,
      "amount": 1769129409.0,
      "turnover": 0.85,
      "open": 9481.07,
      "preClose": 9412.88,
      "mainNet": 2381145.0,
      "rank": 5,
      "passed": 2,
      "qualified": false,
      "score": 49.05,
      "criteria": [
        "[SectorGate] Board rank stays in the front row",
        "[SectorGate] Board momentum remains top-15 positive"
      ],
      "limitUpCount": 0,
      "bigUpCount": 1
    },
    {
      "code": "BK1574",
      "name": "油气开采Ⅲ",
      "kind": "Industry board",
      "price": 3227.12,
      "pct": 2.42,
      "amount": 618227299.0,
      "turnover": 0.76,
      "open": 3233.91,
      "preClose": 3150.82,
      "mainNet": 12175397.0,
      "rank": 6,
      "passed": 2,
      "qualified": false,
      "score": 48.7,
      "criteria": [
        "[SectorGate] Board rank stays in the front row",
        "[SectorGate] Board momentum remains top-15 positive"
      ],
      "limitUpCount": 1,
      "bigUpCount": 2
    },
    {
      "code": "BK1276",
      "name": "油气开采Ⅱ",
      "kind": "Industry board",
      "price": 3226.37,
      "pct": 2.4,
      "amount": 619993442.0,
      "turnover": 0.76,
      "open": 3233.91,
      "preClose": 3150.82,
      "mainNet": 12725622.0,
      "rank": 7,
      "passed": 2,
      "qualified": false,
      "score": 48.35,
      "criteria": [
        "[SectorGate] Board rank stays in the front row",
        "[SectorGate] Board momentum remains top-15 positive"
      ],
      "limitUpCount": 1,
      "bigUpCount": 1
    },
    {
      "code": "BK1608",
      "name": "中药Ⅲ",
      "kind": "Industry board",
      "price": 1281.26,
      "pct": 1.95,
      "amount": 2794588993.0,
      "turnover": 0.45,
      "open": 1262.62,
      "preClose": 1256.75,
      "mainNet": 71872648.0,
      "rank": 11,
      "passed": 2,
      "qualified": false,
      "score": 37,
      "criteria": [
        "Board is near the top of today's movers"
      ],
      "limitUpCount": 0,
      "bigUpCount": 0
    },
    {
      "code": "BK1040",
      "name": "中药Ⅱ",
      "kind": "Industry board",
      "price": 1281.26,
      "pct": 1.95,
      "amount": 2794588993.0,
      "turnover": 0.45,
      "open": 1262.62,
      "preClose": 1256.75,
      "mainNet": 69405955.0,
      "rank": 12,
      "passed": 2,
      "qualified": false,
      "score": 36,
      "criteria": [
        "Board is near the top of today's movers"
      ],
      "limitUpCount": 0,
      "bigUpCount": 0
    }
  ],
  "recommendations": [
    {
      "rank": 1,
      "code": "603065",
      "name": "宿迁联盛",
      "market": "SH",
      "price": 20.76,
      "pct": 6.74,
      "amount": 263579710.0,
      "turnover": 3.11,
      "industry": "化学制品",
      "confidence": 95,
      "winRate": 95,
      "strategyTag": "AM_TOP",
      "t1EdgeScore": 133.72,
      "expectedReturnPct": 5.42,
      "riskPct": 2.73,
      "board": {
        "code": "AM_TOP_eba3c9b2",
        "name": "化学制品",
        "passed": 4,
        "score": 82
      },
      "criteria": {
        "board": [
          "AM_TOP all-main-board scan",
          "Morning top candidate is evaluated by stock shape"
        ],
        "stock": [
          "[AM_TOP] Early morning front-row setup",
          "Board is hot enough for morning acceleration",
          "Morning acceleration gain zone is matched",
          "Price holds the early high platform",
          "Price holds above VWAP",
          "Turnover can support early board capture",
          "Volume is active without obvious exhaustion",
          "Main or super capital is net inflow",
          "Deal amount supports fast T+1 exit",
          "Open has enough upward spread"
        ]
      },
      "buyPlan": {
        "type": "[AM_TOP] 09:31 early lift-off entry",
        "timeWindow": "09:26 watch; 09:31-09:38 primary entry; 09:40+ confirm only",
        "trigger": "Use the first 5-10 minutes to confirm front-row lift-off before the limit-up rush; avoid buying a fade.",
        "priceRange": [
          20.68,
          20.8
        ],
        "quality": 22,
        "priority": 8,
        "strategyTag": "AM_TOP"
      },
      "sellPlan": {
        "targetPrice": 21.8,
        "targetTime": "Next trading day 09:30-10:00; sell before 10:00 unless the board remains sealed.",
        "strategy": "AM_TOP setup: catch the next-morning premium after 09:31-09:38 front-row acceleration; after 09:40 only monitor seal strength or reseal.",
        "takeProfit": 21.8,
        "timeWindow": "Next trading day 09:30-10:00; sell before 10:00 unless the board remains sealed."
      },
      "stopPlan": {
        "stopLoss": 20.13,
        "rules": [
          "Morning top weakens and fails to reseal or hold the high platform",
          "Break the personalized stop or fall back under VWAP with volume",
          "09:26 is a watch/queue signal; 09:31-09:38 is the primary execution window",
          "Do not chase after 09:40 unless it is an unsealed front-row reseal"
        ]
      },
      "sourceLinks": [
        {
          "name": "Eastmoney quote",
          "url": "https://quote.eastmoney.com/sh603065.html"
        },
        {
          "name": "10jqka stock page",
          "url": "https://stockpage.10jqka.com.cn/603065/"
        },
        {
          "name": "Yicai news",
          "url": "https://www.yicai.com/news/"
        }
      ],
      "sparkline": []
    }
  ],
  "news": [
    {
      "source": "Yicai",
      "title": "公告臻选｜捕捉每日公告中的“黄金机会”告别信息过载，把握市场先机，捕捉每天公告中的“黄金机会”。  2025-11-03 14:49",
      "url": "https://www.yicai.com/topic/102892546/",
      "time": ""
    },
    {
      "source": "Yicai",
      "title": "A股四大指数集体低开，市场逾3700股下跌盘面上，半导体、算力硬件产业链调整，存储器、PCB、先进封装方向领跌。  7分钟前",
      "url": "https://www.yicai.com/news/103271319.html",
      "time": ""
    },
    {
      "source": "Yicai",
      "title": "金价震荡蓄势、科技降温回调，资金寻找新均衡中东近期局势再次变化，并未引爆市场避险情绪，三季度补涨预期仍存  昨天 19:37",
      "url": "https://www.yicai.com/news/103270975.html",
      "time": ""
    },
    {
      "source": "Yicai",
      "title": "机构论后市丨调整波段已进入收尾阶段；继续关注三方面配置机会A股后市怎么走？看看机构怎么说。  昨天 17:58",
      "url": "https://www.yicai.com/news/103270964.html",
      "time": ""
    }
  ]
}