{
  "meta": {
    "schemaVersion": 4,
    "generatedAt": "2026-07-08T09:53:39.340203+08:00",
    "tradingDate": "2026-07-08",
    "mode": "fast-snapshot",
    "sourceHealth": [
      {
        "name": "Eastmoney",
        "ok": true,
        "url": "https://push2delay.eastmoney.com/api/qt/clist/get?pn=1&pz=5000&po=1&np=1&ut=bd1d9ddb04089700cf9c27f6f7426281&fltt=2&invt=2&fid=f3&fs=m%3A0%2Bt%3A6%2Cm%3A0%2Bt%3A80%2Cm%3A1%2Bt%3A2%2Cm%3A1%2Bt%3A23&fields=f12%2Cf13%2Cf14%2Cf2%2Cf3%2Cf4%2Cf5%2Cf6%2Cf7%2Cf8%2Cf10%2Cf15%2Cf16%2Cf17%2Cf18%2Cf20%2Cf21%2Cf62%2Cf66%2Cf100",
        "note": "OK"
      },
      {
        "name": "Eastmoney News",
        "ok": true,
        "url": "https://finance.eastmoney.com/a/cjjsp.html",
        "note": "Optional news source OK"
      },
      {
        "name": "10jqka",
        "ok": true,
        "url": "https://www.10jqka.com.cn/",
        "note": "Optional news/reference source"
      },
      {
        "name": "Yicai",
        "ok": true,
        "url": "https://www.yicai.com/",
        "note": "Optional news/reference source"
      }
    ],
    "errors": [],
    "runtimeSeconds": 64.83
  },
  "market": {
    "recommendationCount": 6,
    "qualifiedBoardCount": 7
  },
  "boards": [
    {
      "code": "BK1275",
      "name": "油服工程",
      "kind": "Industry board",
      "price": 1682.38,
      "pct": 4.06,
      "amount": 1903235388.0,
      "turnover": 0.67,
      "open": 1665.44,
      "preClose": 1616.73,
      "mainNet": 209926643.0,
      "rank": 2,
      "passed": 4,
      "qualified": true,
      "score": 82.9,
      "criteria": [
        "Board rank is strong or improving",
        "Limit-up or large-gain members are active",
        "Leader stocks are visible",
        "Board momentum is positive"
      ],
      "limitUpCount": 2,
      "bigUpCount": 4
    },
    {
      "code": "BK1573",
      "name": "油田服务",
      "kind": "Industry board",
      "price": 1492.56,
      "pct": 4.06,
      "amount": 868765280.0,
      "turnover": 0.5,
      "open": 1484.55,
      "preClose": 1434.27,
      "mainNet": 86164905.0,
      "rank": 4,
      "passed": 4,
      "qualified": true,
      "score": 82.2,
      "criteria": [
        "Board rank is strong or improving",
        "Limit-up or large-gain members are active",
        "Leader stocks are visible",
        "Board momentum is positive"
      ],
      "limitUpCount": 2,
      "bigUpCount": 2
    },
    {
      "code": "BK1561",
      "name": "旅游综合",
      "kind": "Industry board",
      "price": 1544.92,
      "pct": 3.76,
      "amount": 521179845.0,
      "turnover": 1.87,
      "open": 1549.49,
      "preClose": 1488.91,
      "mainNet": 44629065.0,
      "rank": 5,
      "passed": 4,
      "qualified": true,
      "score": 81.85,
      "criteria": [
        "Board rank is strong or improving",
        "Limit-up or large-gain members are active",
        "Leader stocks are visible",
        "Board momentum is positive"
      ],
      "limitUpCount": 1,
      "bigUpCount": 4
    },
    {
      "code": "BK1574",
      "name": "油气开采Ⅲ",
      "kind": "Industry board",
      "price": 3177.66,
      "pct": 3.53,
      "amount": 1174214434.0,
      "turnover": 1.1,
      "open": 3153.64,
      "preClose": 3069.18,
      "mainNet": 92049961.0,
      "rank": 7,
      "passed": 4,
      "qualified": true,
      "score": 81.15,
      "criteria": [
        "Board rank is strong or improving",
        "Limit-up or large-gain members are active",
        "Leader stocks are visible",
        "Board momentum is positive"
      ],
      "limitUpCount": 1,
      "bigUpCount": 1
    },
    {
      "code": "BK1276",
      "name": "油气开采Ⅱ",
      "kind": "Industry board",
      "price": 3177.66,
      "pct": 3.53,
      "amount": 1174214434.0,
      "turnover": 1.1,
      "open": 3153.64,
      "preClose": 3069.18,
      "mainNet": 92049961.0,
      "rank": 8,
      "passed": 4,
      "qualified": true,
      "score": 80.8,
      "criteria": [
        "Board rank is strong or improving",
        "Limit-up or large-gain members are active",
        "Leader stocks are visible",
        "Board momentum is positive"
      ],
      "limitUpCount": 1,
      "bigUpCount": 1
    },
    {
      "code": "BK1272",
      "name": "旅游及景区",
      "kind": "Industry board",
      "price": 2805.91,
      "pct": 3.22,
      "amount": 1716521873.0,
      "turnover": 1.48,
      "open": 2803.96,
      "preClose": 2718.38,
      "mainNet": 201059833.0,
      "rank": 9,
      "passed": 4,
      "qualified": true,
      "score": 80.45,
      "criteria": [
        "Board rank is strong or improving",
        "Limit-up or large-gain members are active",
        "Leader stocks are visible",
        "Board momentum is positive"
      ],
      "limitUpCount": 2,
      "bigUpCount": 7
    },
    {
      "code": "BK1051",
      "name": "昨日连板_含一字",
      "kind": "Concept board",
      "price": 26851.88,
      "pct": 2.7,
      "amount": 3848028751.0,
      "turnover": 0.59,
      "open": 26575.02,
      "preClose": 26146.66,
      "mainNet": -34163776.0,
      "rank": 10,
      "passed": 4,
      "qualified": true,
      "score": 80.1,
      "criteria": [
        "Board rank is strong or improving",
        "Limit-up or large-gain members are active",
        "Leader stocks are visible",
        "Board momentum is positive"
      ],
      "limitUpCount": 2,
      "bigUpCount": 3
    },
    {
      "code": "BK1562",
      "name": "人工景区",
      "kind": "Industry board",
      "price": 2597.83,
      "pct": 4.1,
      "amount": 421044287.0,
      "turnover": 1.06,
      "open": 2570.81,
      "preClose": 2495.44,
      "mainNet": 43197525.0,
      "rank": 1,
      "passed": 3,
      "qualified": false,
      "score": 66.85,
      "criteria": [
        "Board rank is strong or improving",
        "Leader stocks are visible",
        "Board momentum is positive"
      ],
      "limitUpCount": 0,
      "bigUpCount": 1
    },
    {
      "code": "BK1572",
      "name": "油气及炼化工程",
      "kind": "Industry board",
      "price": 1558.61,
      "pct": 4.06,
      "amount": 1034470108.0,
      "turnover": 1.05,
      "open": 1533.13,
      "preClose": 1497.85,
      "mainNet": 123761728.0,
      "rank": 3,
      "passed": 3,
      "qualified": false,
      "score": 66.15,
      "criteria": [
        "Board rank is strong or improving",
        "Leader stocks are visible",
        "Board momentum is positive"
      ],
      "limitUpCount": 0,
      "bigUpCount": 2
    },
    {
      "code": "BK1348",
      "name": "辅料",
      "kind": "Industry board",
      "price": 2927.04,
      "pct": 3.74,
      "amount": 435987517.0,
      "turnover": 1.16,
      "open": 2780.62,
      "preClose": 2821.55,
      "mainNet": 25864204.0,
      "rank": 6,
      "passed": 3,
      "qualified": false,
      "score": 65.1,
      "criteria": [
        "Board rank is strong or improving",
        "Leader stocks are visible",
        "Board momentum is positive"
      ],
      "limitUpCount": 0,
      "bigUpCount": 2
    },
    {
      "code": "BK1563",
      "name": "自然景区",
      "kind": "Industry board",
      "price": 2840.43,
      "pct": 2.5,
      "amount": 774297740.0,
      "turnover": 1.46,
      "open": 2841.96,
      "preClose": 2771.04,
      "mainNet": 113233236.0,
      "rank": 11,
      "passed": 2,
      "qualified": false,
      "score": 37,
      "criteria": [
        "Board is near the top of today's movers"
      ],
      "limitUpCount": 0,
      "bigUpCount": 0
    },
    {
      "code": "BK0944",
      "name": "肝素概念",
      "kind": "Concept board",
      "price": 820.77,
      "pct": 2.47,
      "amount": 1063954418.0,
      "turnover": 0.79,
      "open": 800.46,
      "preClose": 801.0,
      "mainNet": 106130399.0,
      "rank": 12,
      "passed": 2,
      "qualified": false,
      "score": 36,
      "criteria": [
        "Board is near the top of today's movers"
      ],
      "limitUpCount": 0,
      "bigUpCount": 0
    }
  ],
  "recommendations": [
    {
      "rank": 1,
      "code": "002396",
      "name": "星网锐捷",
      "market": "SZ",
      "price": 29.1,
      "pct": 10.02,
      "amount": 1435704283.91,
      "turnover": 6.72,
      "industry": "通信设备",
      "confidence": 95,
      "winRate": 95,
      "strategyTag": "AM_TOP",
      "t1EdgeScore": 188.66,
      "expectedReturnPct": 8.39,
      "riskPct": 2.22,
      "board": {
        "code": "AM_TOP_81cd5e3e",
        "name": "通信设备",
        "passed": 4,
        "score": 82
      },
      "criteria": {
        "board": [
          "AM_TOP all-main-board scan",
          "Morning top candidate is evaluated by stock shape"
        ],
        "stock": [
          "[AM_TOP] Morning top setup",
          "Board is hot enough for morning top capture",
          "Morning top gain zone is matched",
          "Price is pinned near the intraday high",
          "Price is far above VWAP",
          "Turnover can support a seal or reseal",
          "Volume is active without obvious exhaustion",
          "Main or super capital is net inflow",
          "Deal amount supports fast T+1 exit",
          "Morning run has enough vertical spread"
        ]
      },
      "buyPlan": {
        "type": "[AM_TOP] 09:40 morning top entry",
        "timeWindow": "09:40-10:00",
        "trigger": "Use only a morning top or near-limit shape; skip if it cannot hold the high platform.",
        "priceRange": [
          28.98,
          29.16
        ],
        "quality": 22,
        "priority": 7,
        "strategyTag": "AM_TOP"
      },
      "sellPlan": {
        "targetPrice": 31.41,
        "targetTime": "Next trading day 09:30-10:00; sell before 10:00 unless the board remains sealed.",
        "strategy": "AM_TOP setup: catch the next-morning premium after a morning top or limit-up hold; exit fast on failure.",
        "takeProfit": 31.41,
        "timeWindow": "Next trading day 09:30-10:00; sell before 10:00 unless the board remains sealed."
      },
      "stopPlan": {
        "stopLoss": 28.35,
        "rules": [
          "Morning top weakens and fails to reseal or hold the high platform",
          "Break the personalized stop or fall back under VWAP with volume",
          "Do not chase after the 09:40-10:00 decision window"
        ]
      },
      "sourceLinks": [
        {
          "name": "Eastmoney quote",
          "url": "https://quote.eastmoney.com/sz002396.html"
        },
        {
          "name": "10jqka stock page",
          "url": "https://stockpage.10jqka.com.cn/002396/"
        },
        {
          "name": "Yicai news",
          "url": "https://www.yicai.com/news/"
        }
      ],
      "sparkline": []
    },
    {
      "rank": 2,
      "code": "603928",
      "name": "兴业股份",
      "market": "SH",
      "price": 16.36,
      "pct": 10.02,
      "amount": 715864683.0,
      "turnover": 13.19,
      "industry": "塑料",
      "confidence": 95,
      "winRate": 95,
      "strategyTag": "AM_TOP",
      "t1EdgeScore": 183.36,
      "expectedReturnPct": 8.59,
      "riskPct": 3.1,
      "board": {
        "code": "AM_TOP_bdc41ee6",
        "name": "塑料",
        "passed": 4,
        "score": 82
      },
      "criteria": {
        "board": [
          "AM_TOP all-main-board scan",
          "Morning top candidate is evaluated by stock shape"
        ],
        "stock": [
          "[AM_TOP] Morning top setup",
          "Board is hot enough for morning top capture",
          "Morning top gain zone is matched",
          "Price is pinned near the intraday high",
          "Price is far above VWAP",
          "Turnover can support a seal or reseal",
          "Volume is active without obvious exhaustion",
          "Main or super capital is net inflow",
          "Deal amount supports fast T+1 exit",
          "Morning run has enough vertical spread"
        ]
      },
      "buyPlan": {
        "type": "[AM_TOP] 09:40 morning top entry",
        "timeWindow": "09:40-10:00",
        "trigger": "Use only a morning top or near-limit shape; skip if it cannot hold the high platform.",
        "priceRange": [
          16.29,
          16.39
        ],
        "quality": 22,
        "priority": 7,
        "strategyTag": "AM_TOP"
      },
      "sellPlan": {
        "targetPrice": 17.69,
        "targetTime": "Next trading day 09:30-10:00; sell before 10:00 unless the board remains sealed.",
        "strategy": "AM_TOP setup: catch the next-morning premium after a morning top or limit-up hold; exit fast on failure.",
        "takeProfit": 17.69,
        "timeWindow": "Next trading day 09:30-10:00; sell before 10:00 unless the board remains sealed."
      },
      "stopPlan": {
        "stopLoss": 15.8,
        "rules": [
          "Morning top weakens and fails to reseal or hold the high platform",
          "Break the personalized stop or fall back under VWAP with volume",
          "Do not chase after the 09:40-10:00 decision window"
        ]
      },
      "sourceLinks": [
        {
          "name": "Eastmoney quote",
          "url": "https://quote.eastmoney.com/sh603928.html"
        },
        {
          "name": "10jqka stock page",
          "url": "https://stockpage.10jqka.com.cn/603928/"
        },
        {
          "name": "Yicai news",
          "url": "https://www.yicai.com/news/"
        }
      ],
      "sparkline": []
    },
    {
      "rank": 3,
      "code": "000759",
      "name": "中百集团",
      "market": "SZ",
      "price": 6.48,
      "pct": 10.02,
      "amount": 354603697.82,
      "turnover": 8.65,
      "industry": "一般零售",
      "confidence": 95,
      "winRate": 95,
      "strategyTag": "AM_TOP",
      "t1EdgeScore": 176.81,
      "expectedReturnPct": 8.37,
      "riskPct": 3.86,
      "board": {
        "code": "AM_TOP_b9071f2b",
        "name": "一般零售",
        "passed": 4,
        "score": 82
      },
      "criteria": {
        "board": [
          "AM_TOP all-main-board scan",
          "Morning top candidate is evaluated by stock shape"
        ],
        "stock": [
          "[AM_TOP] Morning top setup",
          "Board is hot enough for morning top capture",
          "Morning top gain zone is matched",
          "Price is pinned near the intraday high",
          "Price is far above VWAP",
          "Turnover can support a seal or reseal",
          "Volume is active without obvious exhaustion",
          "Main or super capital is net inflow",
          "Deal amount supports fast T+1 exit",
          "Morning run has enough vertical spread"
        ]
      },
      "buyPlan": {
        "type": "[AM_TOP] 09:40 morning top entry",
        "timeWindow": "09:40-10:00",
        "trigger": "Use only a morning top or near-limit shape; skip if it cannot hold the high platform.",
        "priceRange": [
          6.45,
          6.49
        ],
        "quality": 22,
        "priority": 7,
        "strategyTag": "AM_TOP"
      },
      "sellPlan": {
        "targetPrice": 6.99,
        "targetTime": "Next trading day 09:30-10:00; sell before 10:00 unless the board remains sealed.",
        "strategy": "AM_TOP setup: catch the next-morning premium after a morning top or limit-up hold; exit fast on failure.",
        "takeProfit": 6.99,
        "timeWindow": "Next trading day 09:30-10:00; sell before 10:00 unless the board remains sealed."
      },
      "stopPlan": {
        "stopLoss": 6.21,
        "rules": [
          "Morning top weakens and fails to reseal or hold the high platform",
          "Break the personalized stop or fall back under VWAP with volume",
          "Do not chase after the 09:40-10:00 decision window"
        ]
      },
      "sourceLinks": [
        {
          "name": "Eastmoney quote",
          "url": "https://quote.eastmoney.com/sz000759.html"
        },
        {
          "name": "10jqka stock page",
          "url": "https://stockpage.10jqka.com.cn/000759/"
        },
        {
          "name": "Yicai news",
          "url": "https://www.yicai.com/news/"
        }
      ],
      "sparkline": []
    },
    {
      "rank": 4,
      "code": "603496",
      "name": "恒为科技",
      "market": "SH",
      "price": 24.54,
      "pct": 10.0,
      "amount": 256610132.0,
      "turnover": 3.34,
      "industry": "计算机设备",
      "confidence": 95,
      "winRate": 95,
      "strategyTag": "AM_TOP",
      "t1EdgeScore": 173.35,
      "expectedReturnPct": 7.61,
      "riskPct": 2.56,
      "board": {
        "code": "AM_TOP_6d250202",
        "name": "计算机设备",
        "passed": 4,
        "score": 82
      },
      "criteria": {
        "board": [
          "AM_TOP all-main-board scan",
          "Morning top candidate is evaluated by stock shape"
        ],
        "stock": [
          "[AM_TOP] Morning top setup",
          "Board is hot enough for morning top capture",
          "Morning top gain zone is matched",
          "Price is pinned near the intraday high",
          "Price is far above VWAP",
          "Turnover can support a seal or reseal",
          "Volume is active without obvious exhaustion",
          "Main or super capital is net inflow",
          "Deal amount supports fast T+1 exit",
          "Morning run has enough vertical spread"
        ]
      },
      "buyPlan": {
        "type": "[AM_TOP] 09:40 morning top entry",
        "timeWindow": "09:40-10:00",
        "trigger": "Use only a morning top or near-limit shape; skip if it cannot hold the high platform.",
        "priceRange": [
          24.44,
          24.59
        ],
        "quality": 22,
        "priority": 7,
        "strategyTag": "AM_TOP"
      },
      "sellPlan": {
        "targetPrice": 26.3,
        "targetTime": "Next trading day 09:30-10:00; sell before 10:00 unless the board remains sealed.",
        "strategy": "AM_TOP setup: catch the next-morning premium after a morning top or limit-up hold; exit fast on failure.",
        "takeProfit": 26.3,
        "timeWindow": "Next trading day 09:30-10:00; sell before 10:00 unless the board remains sealed."
      },
      "stopPlan": {
        "stopLoss": 23.83,
        "rules": [
          "Morning top weakens and fails to reseal or hold the high platform",
          "Break the personalized stop or fall back under VWAP with volume",
          "Do not chase after the 09:40-10:00 decision window"
        ]
      },
      "sourceLinks": [
        {
          "name": "Eastmoney quote",
          "url": "https://quote.eastmoney.com/sh603496.html"
        },
        {
          "name": "10jqka stock page",
          "url": "https://stockpage.10jqka.com.cn/603496/"
        },
        {
          "name": "Yicai news",
          "url": "https://www.yicai.com/news/"
        }
      ],
      "sparkline": []
    },
    {
      "rank": 5,
      "code": "002038",
      "name": "双鹭药业",
      "market": "SZ",
      "price": 6.41,
      "pct": 9.95,
      "amount": 292726354.18,
      "turnover": 5.51,
      "industry": "化学制药",
      "confidence": 95,
      "winRate": 95,
      "strategyTag": "AM_TOP",
      "t1EdgeScore": 170.72,
      "expectedReturnPct": 7.52,
      "riskPct": 3.07,
      "board": {
        "code": "AM_TOP_4288d15f",
        "name": "化学制药",
        "passed": 4,
        "score": 82
      },
      "criteria": {
        "board": [
          "AM_TOP all-main-board scan",
          "Morning top candidate is evaluated by stock shape"
        ],
        "stock": [
          "[AM_TOP] Morning top setup",
          "Board is hot enough for morning top capture",
          "Morning top gain zone is matched",
          "Price is pinned near the intraday high",
          "Price is far above VWAP",
          "Turnover can support a seal or reseal",
          "Volume is active without obvious exhaustion",
          "Main or super capital is net inflow",
          "Deal amount supports fast T+1 exit",
          "Morning run has enough vertical spread"
        ]
      },
      "buyPlan": {
        "type": "[AM_TOP] 09:40 morning top entry",
        "timeWindow": "09:40-10:00",
        "trigger": "Use only a morning top or near-limit shape; skip if it cannot hold the high platform.",
        "priceRange": [
          6.38,
          6.42
        ],
        "quality": 22,
        "priority": 7,
        "strategyTag": "AM_TOP"
      },
      "sellPlan": {
        "targetPrice": 6.86,
        "targetTime": "Next trading day 09:30-10:00; sell before 10:00 unless the board remains sealed.",
        "strategy": "AM_TOP setup: catch the next-morning premium after a morning top or limit-up hold; exit fast on failure.",
        "takeProfit": 6.86,
        "timeWindow": "Next trading day 09:30-10:00; sell before 10:00 unless the board remains sealed."
      },
      "stopPlan": {
        "stopLoss": 6.19,
        "rules": [
          "Morning top weakens and fails to reseal or hold the high platform",
          "Break the personalized stop or fall back under VWAP with volume",
          "Do not chase after the 09:40-10:00 decision window"
        ]
      },
      "sourceLinks": [
        {
          "name": "Eastmoney quote",
          "url": "https://quote.eastmoney.com/sz002038.html"
        },
        {
          "name": "10jqka stock page",
          "url": "https://stockpage.10jqka.com.cn/002038/"
        },
        {
          "name": "Yicai news",
          "url": "https://www.yicai.com/news/"
        }
      ],
      "sparkline": []
    },
    {
      "rank": 6,
      "code": "600488",
      "name": "津药药业",
      "market": "SH",
      "price": 5.45,
      "pct": 9.22,
      "amount": 519430740.0,
      "turnover": 8.96,
      "industry": "化学制药",
      "confidence": 95,
      "winRate": 95,
      "strategyTag": "AM_TOP",
      "t1EdgeScore": 152.9,
      "expectedReturnPct": 6.45,
      "riskPct": 3.04,
      "board": {
        "code": "AM_TOP_4288d15f",
        "name": "化学制药",
        "passed": 4,
        "score": 82
      },
      "criteria": {
        "board": [
          "AM_TOP all-main-board scan",
          "Morning top candidate is evaluated by stock shape"
        ],
        "stock": [
          "[AM_TOP] Morning top setup",
          "Board is hot enough for morning top capture",
          "Morning top gain zone is matched",
          "Price is pinned near the intraday high",
          "Price is far above VWAP",
          "Turnover can support a seal or reseal",
          "Volume is active without obvious exhaustion",
          "Main or super capital is net inflow",
          "Deal amount supports fast T+1 exit",
          "Morning run has enough vertical spread"
        ]
      },
      "buyPlan": {
        "type": "[AM_TOP] 09:40 morning top entry",
        "timeWindow": "09:40-10:00",
        "trigger": "Use only a morning top or near-limit shape; skip if it cannot hold the high platform.",
        "priceRange": [
          5.43,
          5.46
        ],
        "quality": 22,
        "priority": 7,
        "strategyTag": "AM_TOP"
      },
      "sellPlan": {
        "targetPrice": 5.78,
        "targetTime": "Next trading day 09:30-10:00; sell before 10:00 unless the board remains sealed.",
        "strategy": "AM_TOP setup: catch the next-morning premium after a morning top or limit-up hold; exit fast on failure.",
        "takeProfit": 5.78,
        "timeWindow": "Next trading day 09:30-10:00; sell before 10:00 unless the board remains sealed."
      },
      "stopPlan": {
        "stopLoss": 5.27,
        "rules": [
          "Morning top weakens and fails to reseal or hold the high platform",
          "Break the personalized stop or fall back under VWAP with volume",
          "Do not chase after the 09:40-10:00 decision window"
        ]
      },
      "sourceLinks": [
        {
          "name": "Eastmoney quote",
          "url": "https://quote.eastmoney.com/sh600488.html"
        },
        {
          "name": "10jqka stock page",
          "url": "https://stockpage.10jqka.com.cn/600488/"
        },
        {
          "name": "Yicai news",
          "url": "https://www.yicai.com/news/"
        }
      ],
      "sparkline": []
    }
  ],
  "news": [
    {
      "source": "Eastmoney News",
      "title": "A股三大指数收跌 沪指失守4000点 缩量超5000亿",
      "url": "https://finance.eastmoney.com/a/202607073796666128.html",
      "time": ""
    },
    {
      "source": "Eastmoney News",
      "title": "业绩翻倍甚至好几倍 11家A股公司公布大利好！6倍光通信大牛股在列",
      "url": "https://finance.eastmoney.com/a/202607073797114545.html",
      "time": ""
    },
    {
      "source": "Eastmoney News",
      "title": "PCB产品涨价10%—15%！A股公司宣布三度调价",
      "url": "https://finance.eastmoney.com/a/202607073796689241.html",
      "time": ""
    },
    {
      "source": "Eastmoney News",
      "title": "A股波动大如何守住利润？“黑天鹅”尾部风险管理是答案吗｜对话瑞锐投资袁磊",
      "url": "https://finance.eastmoney.com/a/202605073730389683.html",
      "time": ""
    },
    {
      "source": "Eastmoney News",
      "title": "掘金2026年A股中报季",
      "url": "https://topic.eastmoney.com/detail/agzbj2026.html",
      "time": ""
    },
    {
      "source": "Eastmoney News",
      "title": "A股交易新规！7月6日正式施行",
      "url": "https://topic.eastmoney.com/detail/agjyxg2026.html",
      "time": ""
    },
    {
      "source": "Eastmoney News",
      "title": "中信证券：大幅波动不改AI超级周期 重视国产算力“Plan B”",
      "url": "https://finance.eastmoney.com/a/202607083797406338.html",
      "time": ""
    },
    {
      "source": "Eastmoney News",
      "title": "中信证券：预计焦煤、无烟煤公司业绩增速或有更好的弹性",
      "url": "https://finance.eastmoney.com/a/202607083797372037.html",
      "time": ""
    }
  ]
}